down_frab_videos/__init__.py
down_frab_videos/config.py
down_frab_videos-0.5.10.data/scripts/down-frab-videos
down_frab_videos-0.5.10.dist-info/licenses/LICENSE
down_frab_videos-0.5.10.dist-info/METADATA
down_frab_videos-0.5.10.dist-info/WHEEL
down_frab_videos-0.5.10.dist-info/top_level.txt
down_frab_videos-0.5.10.dist-info/RECORD
