Metadata-Version: 2.4
Name: down-frab-videos
Version: 0.5.10
Summary: Download videos and lecture attachments from CCC events
Home-page: https://github.com/mfherbst/down-frab-videos
Author: Michael F. Herbst
Author-email: info@michael-herbst.com
License: GPL v3
Classifier: Development Status :: 4 - Beta
Classifier: Environment :: Console
Classifier: License :: OSI Approved :: GNU General Public License v3 (GPLv3)
Classifier: Intended Audience :: Information Technology
Classifier: Topic :: Internet :: WWW/HTTP :: Indexing/Search
Classifier: Programming Language :: Python :: 3.5
Classifier: Programming Language :: Python :: 3.6
Classifier: Operating System :: Unix
Requires-Python: >=3
License-File: LICENSE
Requires-Dist: beautifulsoup4>=4.2
Requires-Dist: lxml>=4.2
Requires-Dist: pycountry>=17.5.14
Requires-Dist: PyYAML>=3.12
Requires-Dist: requests>=2.2
Dynamic: author
Dynamic: author-email
Dynamic: classifier
Dynamic: description
Dynamic: home-page
Dynamic: license
Dynamic: license-file
Dynamic: requires-dist
Dynamic: requires-python
Dynamic: summary
